{
	"animations": [
		{
			"loop": false,
			"offsets": [
				311,
				21
			],
			"fps": 24,
			"anim": "singLEFT",
			"indices": [],
			"name": "Dad Sing Note LEFT"
		},
		{
			"loop": false,
			"offsets": [
				200,
				-60
			],
			"fps": 24,
			"anim": "singDOWN",
			"indices": [],
			"name": "Dad Sing Note DOWN"
		},
		{
			"loop": false,
			"offsets": [
				194,
				100
			],
			"fps": 24,
			"anim": "singUP",
			"indices": [],
			"name": "Dad Sing Note UP"
		},
		{
			"loop": false,
			"offsets": [
				194,
				60
			],
			"fps": 24,
			"anim": "singRIGHT",
			"indices": [],
			"name": "Dad Sing Note RIGHT"
		},
		{
			"loop": false,
			"offsets": [
				180,
				45
			],
			"fps": 24,
			"anim": "idle",
			"indices": [],
			"name": "Dad idle dance"
		}
	],
	"no_antialiasing": false,
	"image": "characters/tabi",
	"position": [
		0,
		0
	],
	"healthicon": "icon_tabi",
	"flip_x": false,
	"healthbar_colors": [
		255,
		202,
		146
	],
	"camera_position": [
		100,
		0
	],
	"sing_duration": 6.1,
	"scale": 1
}